{
  "ran": "2026-07-15T21:59:31.268Z",
  "api": "https://api.apievangelist.com/v1",
  "ruleset": "apis-io-spectral-rules.yml",
  "totals": {
    "apis": 12,
    "operations": 64,
    "errors": 0,
    "warnings": 230,
    "info": 447,
    "hints": 0,
    "findings": 677,
    "passing": 12
  },
  "apis": [
    {
      "tag": "Providers",
      "ops": 6,
      "rules": 42,
      "errors": 0,
      "warnings": 25,
      "info": 67,
      "hints": 0,
      "findings": 92,
      "passed": true,
      "coverage": 94,
      "score": 98,
      "grade": "A"
    },
    {
      "tag": "APIs",
      "ops": 5,
      "rules": 42,
      "errors": 0,
      "warnings": 21,
      "info": 37,
      "hints": 0,
      "findings": 58,
      "passed": true,
      "coverage": 94,
      "score": 98,
      "grade": "A"
    },
    {
      "tag": "Tags",
      "ops": 2,
      "rules": 42,
      "errors": 0,
      "warnings": 8,
      "info": 59,
      "hints": 0,
      "findings": 67,
      "passed": true,
      "coverage": 93,
      "score": 98,
      "grade": "A"
    },
    {
      "tag": "Industries",
      "ops": 3,
      "rules": 42,
      "errors": 0,
      "warnings": 11,
      "info": 30,
      "hints": 0,
      "findings": 41,
      "passed": true,
      "coverage": 96,
      "score": 98,
      "grade": "A"
    },
    {
      "tag": "Regions",
      "ops": 3,
      "rules": 42,
      "errors": 0,
      "warnings": 11,
      "info": 31,
      "hints": 0,
      "findings": 42,
      "passed": true,
      "coverage": 96,
      "score": 98,
      "grade": "A"
    },
    {
      "tag": "Areas",
      "ops": 3,
      "rules": 42,
      "errors": 0,
      "warnings": 11,
      "info": 33,
      "hints": 0,
      "findings": 44,
      "passed": true,
      "coverage": 96,
      "score": 98,
      "grade": "A"
    },
    {
      "tag": "Synthesis",
      "ops": 6,
      "rules": 42,
      "errors": 0,
      "warnings": 19,
      "info": 7,
      "hints": 0,
      "findings": 26,
      "passed": true,
      "coverage": 90,
      "score": 96,
      "grade": "A"
    },
    {
      "tag": "Ratings",
      "ops": 5,
      "rules": 42,
      "errors": 0,
      "warnings": 18,
      "info": 37,
      "hints": 0,
      "findings": 55,
      "passed": true,
      "coverage": 91,
      "score": 97,
      "grade": "A"
    },
    {
      "tag": "Artifact Types",
      "ops": 20,
      "rules": 42,
      "errors": 0,
      "warnings": 60,
      "info": 24,
      "hints": 0,
      "findings": 84,
      "passed": true,
      "coverage": 93,
      "score": 97,
      "grade": "A"
    },
    {
      "tag": "Search",
      "ops": 1,
      "rules": 42,
      "errors": 0,
      "warnings": 5,
      "info": 80,
      "hints": 0,
      "findings": 85,
      "passed": true,
      "coverage": 93,
      "score": 98,
      "grade": "A"
    },
    {
      "tag": "Insights",
      "ops": 8,
      "rules": 42,
      "errors": 0,
      "warnings": 32,
      "info": 7,
      "hints": 0,
      "findings": 39,
      "passed": true,
      "coverage": 84,
      "score": 93,
      "grade": "A"
    },
    {
      "tag": "Submit",
      "ops": 2,
      "rules": 42,
      "errors": 0,
      "warnings": 9,
      "info": 35,
      "hints": 0,
      "findings": 44,
      "passed": true,
      "coverage": 85,
      "score": 95,
      "grade": "A"
    }
  ]
}
